eib_aws_utils/__init__.py
eib_aws_utils/api.py
eib_aws_utils/backgound_job.py
eib_aws_utils/dynamo_utils.py
eib_aws_utils/errors.py
eib_aws_utils/http_utils.py
eib_aws_utils/logging.py
eib_aws_utils-2.0.0.dist-info/LICENSE.txt
eib_aws_utils-2.0.0.dist-info/METADATA
eib_aws_utils-2.0.0.dist-info/WHEEL
eib_aws_utils-2.0.0.dist-info/top_level.txt
eib_aws_utils-2.0.0.dist-info/RECORD
