Metadata-Version: 2.1
Name: eib-aws-utils
Version: 2.0.0
Summary: Helper used by Engie Impact Sustainability Solution EMEAI to develop services based on AWS
Home-page: https://github.tools.digital.engie.com/TractebelHQImpulse/eib-aws-utils
Author: Engie Impact Sustainability Solution EMEAI
Author-email: guido.maurano@engie.com
Classifier: Programming Language :: Python :: 3
Classifier: Operating System :: OS Independent
Requires-Python: >=3.9
License-File: LICENSE.txt
Requires-Dist: python-json-logger
Requires-Dist: requests
